quibbler/__init__.py
quibbler/agent.py
quibbler/cli.py
quibbler/hook_display.py
quibbler/hook_forward.py
quibbler/logger.py
quibbler/prompts.py
quibbler/server.py
quibbler-0.1.5.dist-info/METADATA
quibbler-0.1.5.dist-info/WHEEL
quibbler-0.1.5.dist-info/entry_points.txt
quibbler-0.1.5.dist-info/licenses/LICENSE
quibbler-0.1.5.dist-info/RECORD
