Metadata-Version: 2.4
Name: quibbler
Version: 0.1.5
Summary: AI monitoring for Claude Code agents
License-File: LICENSE
Requires-Python: >=3.12
Requires-Dist: claude-agent-sdk>=0.1.0
Requires-Dist: fastapi>=0.117.1
Requires-Dist: requests>=2.30.0
Requires-Dist: uvicorn>=0.37.0
